[
  {
    "stt": 1,
    "name": "Đức",
    "slug": "duc-3bf62d55ecfc-959e7eed",
    "group": "Bạn Học 12D",
    "area": "Bình Thạnh",
    "inviteUrl": "https://wedding-us-one.vercel.app/?guest=duc-3bf62d55ecfc-959e7eed"
  },
  {
    "stt": 2,
    "name": "Việt",
    "slug": "viet-b05cef8da0e6-1e3bd2c5",
    "group": "Bạn Học 12D",
    "area": "Bình Thạnh",
    "inviteUrl": "https://wedding-us-one.vercel.app/?guest=viet-b05cef8da0e6-1e3bd2c5"
  },
  {
    "stt": 3,
    "name": "Thành",
    "slug": "xuan-thanh-8efa0fbb09b7-196b80b6",
    "group": "Bạn Học 12D",
    "area": "Bình Thạnh",
    "inviteUrl": "https://wedding-us-one.vercel.app/?guest=xuan-thanh-8efa0fbb09b7-196b80b6"
  },
  {
    "stt": 4,
    "name": "Tùng",
    "slug": "tung-462a41fec7f1-3d557617",
    "group": "Bạn Học 12D",
    "area": "Bình Thạnh",
    "inviteUrl": "https://wedding-us-one.vercel.app/?guest=tung-462a41fec7f1-3d557617"
  },
  {
    "stt": 5,
    "name": "Minh",
    "slug": "minh-b10f733d4d8e-b31ca113",
    "group": "Bạn Học 12D",
    "area": "Bình Thạnh",
    "inviteUrl": "https://wedding-us-one.vercel.app/?guest=minh-b10f733d4d8e-b31ca113"
  },
  {
    "stt": 6,
    "name": "An",
    "slug": "an-1c7476370189-d3893992",
    "group": "Bạn Học 12D",
    "area": "Bình Thạnh",
    "inviteUrl": "https://wedding-us-one.vercel.app/?guest=an-1c7476370189-d3893992"
  },
  {
    "stt": 7,
    "name": "Nguyệt",
    "slug": "nguyet-2d1060fadc20-be60887e",
    "group": "Bạn Học 12D",
    "area": "Thôn 2",
    "inviteUrl": "https://wedding-us-one.vercel.app/?guest=nguyet-2d1060fadc20-be60887e"
  },
  {
    "stt": 8,
    "name": "Xoan",
    "slug": "xoan-f68069826990-69d100ad",
    "group": "Bạn Học 12D",
    "area": "Thôn 2",
    "inviteUrl": "https://wedding-us-one.vercel.app/?guest=xoan-f68069826990-69d100ad"
  },
  {
    "stt": 9,
    "name": "Tín",
    "slug": "tin-b66d0bae5674-9c89ae8a",
    "group": "Bạn Học 12D",
    "area": "Thôn 2",
    "inviteUrl": "https://wedding-us-one.vercel.app/?guest=tin-b66d0bae5674-9c89ae8a"
  },
  {
    "stt": 10,
    "name": "Khanh",
    "slug": "cong-khanh-51ab96a9651e-0deea2d1",
    "group": "Bạn Học 12D",
    "area": "Thôn 2",
    "inviteUrl": "https://wedding-us-one.vercel.app/?guest=cong-khanh-51ab96a9651e-0deea2d1"
  },
  {
    "stt": 11,
    "name": "Phong",
    "slug": "phong-870acbe57861-c3a27298",
    "group": "Bạn Học 12D",
    "area": "Thôn 3",
    "inviteUrl": "https://wedding-us-one.vercel.app/?guest=phong-870acbe57861-c3a27298"
  },
  {
    "stt": 12,
    "name": "Hoàng",
    "slug": "hoang-5787899db277-1906c3a5",
    "group": "Bạn Học 12D",
    "area": "Thôn 3",
    "inviteUrl": "https://wedding-us-one.vercel.app/?guest=hoang-5787899db277-1906c3a5"
  },
  {
    "stt": 13,
    "name": "Thuỷ",
    "slug": "thuy-4484d449140a-cda4fadd",
    "group": "Bạn Học 12D",
    "area": "Thôn 3",
    "inviteUrl": "https://wedding-us-one.vercel.app/?guest=thuy-4484d449140a-cda4fadd"
  },
  {
    "stt": 14,
    "name": "Nhi",
    "slug": "yen-nhi-23b22ff61e66-6b9bfc62",
    "group": "Bạn Học 12D",
    "area": "Thôn 3",
    "inviteUrl": "https://wedding-us-one.vercel.app/?guest=yen-nhi-23b22ff61e66-6b9bfc62"
  },
  {
    "stt": 15,
    "name": "Thành",
    "slug": "tan-thanh-68630fd39b0c-979610cb",
    "group": "Bạn Học 12D",
    "area": "Thôn 5",
    "inviteUrl": "https://wedding-us-one.vercel.app/?guest=tan-thanh-68630fd39b0c-979610cb"
  },
  {
    "stt": 16,
    "name": "Danh",
    "slug": "danh-5ed5bc5d374e-cff41cd6",
    "group": "Bạn Học 12D",
    "area": "Thôn 5",
    "inviteUrl": "https://wedding-us-one.vercel.app/?guest=danh-5ed5bc5d374e-cff41cd6"
  },
  {
    "stt": 17,
    "name": "Nhi",
    "slug": "nhi-huynh-2781c01d4c43-dfcacfbe",
    "group": "Bạn Học 12D",
    "area": "Thôn 5",
    "inviteUrl": "https://wedding-us-one.vercel.app/?guest=nhi-huynh-2781c01d4c43-dfcacfbe"
  },
  {
    "stt": 18,
    "name": "Nhi",
    "slug": "hong-nhi-c954b5bc7aab-bbd132b8",
    "group": "Bạn Học 12D",
    "area": "Thôn 5",
    "inviteUrl": "https://wedding-us-one.vercel.app/?guest=hong-nhi-c954b5bc7aab-bbd132b8"
  },
  {
    "stt": 19,
    "name": "Huy",
    "slug": "huy-569708502730-6803a3df",
    "group": "Bạn Học 12D",
    "area": "Thôn 6",
    "inviteUrl": "https://wedding-us-one.vercel.app/?guest=huy-569708502730-6803a3df"
  },
  {
    "stt": 20,
    "name": "Hoa",
    "slug": "hoa-ac906cc920bf-2c654d40",
    "group": "Bạn Học 12D",
    "area": "Thôn 6",
    "inviteUrl": "https://wedding-us-one.vercel.app/?guest=hoa-ac906cc920bf-2c654d40"
  },
  {
    "stt": 21,
    "name": "Sang",
    "slug": "sang-e5dcbcaaecf1-a9755e59",
    "group": "Bạn Học 12D",
    "area": "Thôn 7",
    "inviteUrl": "https://wedding-us-one.vercel.app/?guest=sang-e5dcbcaaecf1-a9755e59"
  },
  {
    "stt": 22,
    "name": "Hiền",
    "slug": "hien-51305d8752d7-056b01cb",
    "group": "Bạn Học 9C",
    "area": "Thôn 3",
    "inviteUrl": "https://wedding-us-one.vercel.app/?guest=hien-51305d8752d7-056b01cb"
  },
  {
    "stt": 23,
    "name": "Mỹ",
    "slug": "ngo-my-e60303932f4d-5eb977c4",
    "group": "Bạn Học 9C",
    "area": "Bình Thạnh",
    "inviteUrl": "https://wedding-us-one.vercel.app/?guest=ngo-my-e60303932f4d-5eb977c4"
  },
  {
    "stt": 24,
    "name": "Quỳnh",
    "slug": "quynh-de685d8eb4ed-65b53725",
    "group": "Bạn Học 9C",
    "area": "Thôn 2",
    "inviteUrl": "https://wedding-us-one.vercel.app/?guest=quynh-de685d8eb4ed-65b53725"
  },
  {
    "stt": 25,
    "name": "Tới",
    "slug": "toi-a15a9e02a5af-35d284d5",
    "group": "Bạn Học 9C",
    "area": "Thôn 2",
    "inviteUrl": "https://wedding-us-one.vercel.app/?guest=toi-a15a9e02a5af-35d284d5"
  },
  {
    "stt": 26,
    "name": "Khởi",
    "slug": "khoi-1ade683e20a3-b0d3e6ee",
    "group": "Bạn Học 9C",
    "area": "Thôn 2",
    "inviteUrl": "https://wedding-us-one.vercel.app/?guest=khoi-1ade683e20a3-b0d3e6ee"
  },
  {
    "stt": 27,
    "name": "Hoàn",
    "slug": "hoan-935b4d050290-751c10da",
    "group": "Bạn Học 9C",
    "area": "Thôn 2",
    "inviteUrl": "https://wedding-us-one.vercel.app/?guest=hoan-935b4d050290-751c10da"
  },
  {
    "stt": 28,
    "name": "thầy Sang",
    "slug": "thay-sang-e4a077dabbc1-76acf501",
    "group": "Khác",
    "area": "Thôn 7",
    "inviteUrl": "https://wedding-us-one.vercel.app/?guest=thay-sang-e4a077dabbc1-76acf501"
  },
  {
    "stt": 29,
    "name": "Diệp",
    "slug": "diep-0e17426b562c-74e39835",
    "group": "Hàng xóm",
    "area": "Thôn 2",
    "inviteUrl": "https://wedding-us-one.vercel.app/?guest=diep-0e17426b562c-74e39835"
  },
  {
    "stt": 30,
    "name": "Thọ",
    "slug": "tho-83b83e649e80-83c0e8fe",
    "group": "Hàng xóm",
    "area": "Thôn 2",
    "inviteUrl": "https://wedding-us-one.vercel.app/?guest=tho-83b83e649e80-83c0e8fe"
  },
  {
    "stt": 31,
    "name": "chị Hồng",
    "slug": "chi-hong-385620fce3a1-dc6edc66",
    "group": "Hàng xóm",
    "area": "Thôn 2",
    "inviteUrl": "https://wedding-us-one.vercel.app/?guest=chi-hong-385620fce3a1-dc6edc66"
  },
  {
    "stt": 32,
    "name": "chị Ly",
    "slug": "chi-ly-50367a247636-ad484cfb",
    "group": "Hàng xóm",
    "area": "Thôn 2",
    "inviteUrl": "https://wedding-us-one.vercel.app/?guest=chi-ly-50367a247636-ad484cfb"
  },
  {
    "stt": 33,
    "name": "anh Thạnh",
    "slug": "anh-thanh-daae8085263e-ea26e732",
    "group": "Hàng xóm",
    "area": "Thôn 2",
    "inviteUrl": "https://wedding-us-one.vercel.app/?guest=anh-thanh-daae8085263e-ea26e732"
  },
  {
    "stt": 34,
    "name": "chị Bình",
    "slug": "chi-binh-f4b8d8369039-60454a2d",
    "group": "Hàng xóm",
    "area": "Thôn 2",
    "inviteUrl": "https://wedding-us-one.vercel.app/?guest=chi-binh-f4b8d8369039-60454a2d"
  },
  {
    "stt": 35,
    "name": "em Trúc",
    "slug": "em-truc-15a6dc7c1d4d-ba40b198",
    "group": "Hàng xóm",
    "area": "Thôn 2",
    "inviteUrl": "https://wedding-us-one.vercel.app/?guest=em-truc-15a6dc7c1d4d-ba40b198"
  },
  {
    "stt": 36,
    "name": "anh Phong",
    "slug": "anh-phong-cb931805b6a3-bd1cadec",
    "group": "Hàng xóm",
    "area": "Thôn 2",
    "inviteUrl": "https://wedding-us-one.vercel.app/?guest=anh-phong-cb931805b6a3-bd1cadec"
  },
  {
    "stt": 37,
    "name": "chị Sáng",
    "slug": "chi-sang-c9165a17481b-a18d8726",
    "group": "Hàng xóm",
    "area": "Thôn 2",
    "inviteUrl": "https://wedding-us-one.vercel.app/?guest=chi-sang-c9165a17481b-a18d8726"
  },
  {
    "stt": 38,
    "name": "Toàn",
    "slug": "toan-b40f88abc312-47ea5b05",
    "group": "Đá Banh năm xưa",
    "area": "Thôn 2",
    "inviteUrl": "https://wedding-us-one.vercel.app/?guest=toan-b40f88abc312-47ea5b05"
  },
  {
    "stt": 39,
    "name": "Bảo",
    "slug": "bao-cdaf9c218a61-ba753915",
    "group": "Đá Banh năm xưa",
    "area": "Thôn 2",
    "inviteUrl": "https://wedding-us-one.vercel.app/?guest=bao-cdaf9c218a61-ba753915"
  },
  {
    "stt": 40,
    "name": "Diễn",
    "slug": "dien-3d0996b4f1a1-36e5fbc2",
    "group": "Đá Banh năm xưa",
    "area": "Thôn 2",
    "inviteUrl": "https://wedding-us-one.vercel.app/?guest=dien-3d0996b4f1a1-36e5fbc2"
  },
  {
    "stt": 41,
    "name": "Định",
    "slug": "dinh-539ad9ce6afe-67582a87",
    "group": "Đá Banh năm xưa",
    "area": "Thôn 2",
    "inviteUrl": "https://wedding-us-one.vercel.app/?guest=dinh-539ad9ce6afe-67582a87"
  },
  {
    "stt": 42,
    "name": "Nguyên",
    "slug": "nguyen-1168d9383711-9bef934f",
    "group": "Đá Banh năm xưa",
    "area": "Thôn 2",
    "inviteUrl": "https://wedding-us-one.vercel.app/?guest=nguyen-1168d9383711-9bef934f"
  },
  {
    "stt": 43,
    "name": "anh Vinh",
    "slug": "anh-vinh-f59a017fc448-941dc088",
    "group": "Họ hàng",
    "area": "Thôn 2",
    "inviteUrl": "https://wedding-us-one.vercel.app/?guest=anh-vinh-f59a017fc448-941dc088"
  },
  {
    "stt": 44,
    "name": "chị Hằng",
    "slug": "chi-hang-eb7e126521b0-256248f2",
    "group": "Họ hàng",
    "area": "Thôn 2",
    "inviteUrl": "https://wedding-us-one.vercel.app/?guest=chi-hang-eb7e126521b0-256248f2"
  },
  {
    "stt": 45,
    "name": "chị Bành",
    "slug": "chi-banh-a3a2acebceff-3c244a75",
    "group": "Họ hàng",
    "area": "Thôn 2",
    "inviteUrl": "https://wedding-us-one.vercel.app/?guest=chi-banh-a3a2acebceff-3c244a75"
  },
  {
    "stt": 46,
    "name": "anh Tàu",
    "slug": "anh-tau-fbebc6ed7e1e-0430c42b",
    "group": "Họ hàng",
    "area": "Thôn 2",
    "inviteUrl": "https://wedding-us-one.vercel.app/?guest=anh-tau-fbebc6ed7e1e-0430c42b"
  },
  {
    "stt": 47,
    "name": "Quốc",
    "slug": "quoc-daf4523d6405-859a3663",
    "group": "Ae xã giao",
    "area": "Bình Thạnh",
    "inviteUrl": "https://wedding-us-one.vercel.app/?guest=quoc-daf4523d6405-859a3663"
  },
  {
    "stt": 48,
    "name": "a Tân",
    "slug": "a-tan-639c04df0aa1-6dfe15fd",
    "group": "Ae xã giao",
    "area": "Bình Thạnh",
    "inviteUrl": "https://wedding-us-one.vercel.app/?guest=a-tan-639c04df0aa1-6dfe15fd"
  },
  {
    "stt": 49,
    "name": "a Trọng",
    "slug": "ngo-trong-fcb9893a5ca0-5796d69b",
    "group": "Ae xã giao",
    "area": "Thôn 2",
    "inviteUrl": "https://wedding-us-one.vercel.app/?guest=ngo-trong-fcb9893a5ca0-5796d69b"
  },
  {
    "stt": 50,
    "name": "anh Diễn",
    "slug": "anh-dien-0616eb99ab4f-46da183f",
    "group": "Ae xã giao",
    "area": "Thôn 3",
    "inviteUrl": "https://wedding-us-one.vercel.app/?guest=anh-dien-0616eb99ab4f-46da183f"
  },
  {
    "stt": 51,
    "name": "em Nam Sin",
    "slug": "em-nam-sin-81f099b9e9aa-4532bb62",
    "group": "Ae xã giao",
    "area": "Thôn 2",
    "inviteUrl": "https://wedding-us-one.vercel.app/?guest=em-nam-sin-81f099b9e9aa-4532bb62"
  },
  {
    "stt": 52,
    "name": "Phương",
    "slug": "minh-phuong-e6dd53655304-dc565bee",
    "group": "Ae xã giao",
    "area": "Phú Yên",
    "inviteUrl": "https://wedding-us-one.vercel.app/?guest=minh-phuong-e6dd53655304-dc565bee"
  },
  {
    "stt": 53,
    "name": "Ngọc",
    "slug": "thanh-ngoc-791651d5162a-a3e6bbb9",
    "group": "Ae xã giao",
    "area": "Quy Nhơn",
    "inviteUrl": "https://wedding-us-one.vercel.app/?guest=thanh-ngoc-791651d5162a-a3e6bbb9"
  },
  {
    "stt": 54,
    "name": "a Lâm",
    "slug": "a-lam-duyen-790a30c96cb2-f8b0c9b3",
    "group": "Ae xã giao",
    "area": "Thôn 2",
    "inviteUrl": "https://wedding-us-one.vercel.app/?guest=a-lam-duyen-790a30c96cb2-f8b0c9b3"
  },
  {
    "stt": 55,
    "name": "a Tú",
    "slug": "a-tu-50e846fcd3a5-6d903466",
    "group": "Ae xã giao",
    "area": "Quy Nhơn",
    "inviteUrl": "https://wedding-us-one.vercel.app/?guest=a-tu-50e846fcd3a5-6d903466"
  },
  {
    "stt": 56,
    "name": "a Đức",
    "slug": "a-duc-qui-vi-07106c2f41a1-2febb01c",
    "group": "Hàng xóm",
    "area": "Thôn 2",
    "inviteUrl": "https://wedding-us-one.vercel.app/?guest=a-duc-qui-vi-07106c2f41a1-2febb01c"
  },
  {
    "stt": 57,
    "name": "anh Tiến",
    "slug": "anh-tien-b74f988fd5b0-c65db24f",
    "group": "Hàng xóm",
    "area": "Thôn 2",
    "inviteUrl": "https://wedding-us-one.vercel.app/?guest=anh-tien-b74f988fd5b0-c65db24f"
  },
  {
    "stt": 58,
    "name": "Duy",
    "slug": "duy-f00575c528dc-23acfe16",
    "group": "Bạn học ĐH",
    "area": "Quy Nhơn",
    "inviteUrl": "https://wedding-us-one.vercel.app/?guest=duy-f00575c528dc-23acfe16"
  },
  {
    "stt": 59,
    "name": "Nghĩa",
    "slug": "nghia-94a913d7f861-7f553838",
    "group": "Bạn học ĐH",
    "area": "Quy Nhơn",
    "inviteUrl": "https://wedding-us-one.vercel.app/?guest=nghia-94a913d7f861-7f553838"
  },
  {
    "stt": 60,
    "name": "anh Tín",
    "slug": "anh-tin-267c52ff982b-431fdde3",
    "group": "Bạn học ĐH",
    "area": "Quy Nhơn",
    "inviteUrl": "https://wedding-us-one.vercel.app/?guest=anh-tin-267c52ff982b-431fdde3"
  },
  {
    "stt": 61,
    "name": "Tình",
    "slug": "tinh-263cb5ffda6e-6de46153",
    "group": "Bạn học ĐH",
    "area": "Quy Nhơn",
    "inviteUrl": "https://wedding-us-one.vercel.app/?guest=tinh-263cb5ffda6e-6de46153"
  },
  {
    "stt": 62,
    "name": "Quý",
    "slug": "quy-569b4cc4cccd-cd85a38c",
    "group": "Bạn học ĐH",
    "area": "Phú Yên",
    "inviteUrl": "https://wedding-us-one.vercel.app/?guest=quy-569b4cc4cccd-cd85a38c"
  },
  {
    "stt": 63,
    "name": "Thành",
    "slug": "thanh-d6a0479ea65c-8735a522",
    "group": "Bạn học ĐH",
    "area": "Quy Nhơn",
    "inviteUrl": "https://wedding-us-one.vercel.app/?guest=thanh-d6a0479ea65c-8735a522"
  },
  {
    "stt": 64,
    "name": "Đức",
    "slug": "duc-eaf85977d2da-f472151e",
    "group": "Bạn học ĐH",
    "area": "Quy Nhơn",
    "inviteUrl": "https://wedding-us-one.vercel.app/?guest=duc-eaf85977d2da-f472151e"
  },
  {
    "stt": 65,
    "name": "Việt",
    "slug": "viet-4264e358054d-f3ed99d1",
    "group": "Bạn học ĐH",
    "area": "Quy Nhơn",
    "inviteUrl": "https://wedding-us-one.vercel.app/?guest=viet-4264e358054d-f3ed99d1"
  },
  {
    "stt": 66,
    "name": "Ân",
    "slug": "an-abeaa247fa2b-4f7cda5b",
    "group": "Bạn học ĐH",
    "area": "Quy Nhơn",
    "inviteUrl": "https://wedding-us-one.vercel.app/?guest=an-abeaa247fa2b-4f7cda5b"
  },
  {
    "stt": 67,
    "name": "Trường",
    "slug": "hang-truong-a5f8266cd285-7f428e51",
    "group": "Bạn học ĐH",
    "area": "Quy Nhơn",
    "inviteUrl": "https://wedding-us-one.vercel.app/?guest=hang-truong-a5f8266cd285-7f428e51"
  },
  {
    "stt": 68,
    "name": "Pháp",
    "slug": "phap-7f38d80d377f-d67e4b51",
    "group": "Bạn học ĐH",
    "area": "Quy Nhơn",
    "inviteUrl": "https://wedding-us-one.vercel.app/?guest=phap-7f38d80d377f-d67e4b51"
  },
  {
    "stt": 69,
    "name": "Tới",
    "slug": "toi-5e118b2e758f-d9062b0b",
    "group": "Bạn học ĐH",
    "area": "Quy Nhơn",
    "inviteUrl": "https://wedding-us-one.vercel.app/?guest=toi-5e118b2e758f-d9062b0b"
  },
  {
    "stt": 70,
    "name": "Quốc",
    "slug": "quoc-1fb1e12bb036-dbe24cc6",
    "group": "Bạn học ĐH",
    "area": "Quy Nhơn",
    "inviteUrl": "https://wedding-us-one.vercel.app/?guest=quoc-1fb1e12bb036-dbe24cc6"
  },
  {
    "stt": 71,
    "name": "anh Thiết",
    "slug": "anh-thiet-2076c1d5c01e-40d4fd38",
    "group": "TMA SG",
    "area": "Sài Gòn",
    "inviteUrl": "https://wedding-us-one.vercel.app/?guest=anh-thiet-2076c1d5c01e-40d4fd38"
  },
  {
    "stt": 72,
    "name": "chị Trâm",
    "slug": "chi-tram-755d932c1de7-02ae7d54",
    "group": "TMA SG",
    "area": "",
    "inviteUrl": "https://wedding-us-one.vercel.app/?guest=chi-tram-755d932c1de7-02ae7d54"
  },
  {
    "stt": 73,
    "name": "anh Công",
    "slug": "anh-cong-fe88f5ccd468-f9486fc0",
    "group": "TMA SG",
    "area": "",
    "inviteUrl": "https://wedding-us-one.vercel.app/?guest=anh-cong-fe88f5ccd468-f9486fc0"
  },
  {
    "stt": 74,
    "name": "e Việt",
    "slug": "e-viet-eac05a856537-db4c00db",
    "group": "TMA SG",
    "area": "",
    "inviteUrl": "https://wedding-us-one.vercel.app/?guest=e-viet-eac05a856537-db4c00db"
  },
  {
    "stt": 75,
    "name": "a Doanh",
    "slug": "a-doanh-adfcea16c917-a41e9bcc",
    "group": "TMA SG",
    "area": "",
    "inviteUrl": "https://wedding-us-one.vercel.app/?guest=a-doanh-adfcea16c917-a41e9bcc"
  },
  {
    "stt": 76,
    "name": "chị Nhung",
    "slug": "chi-nhung-e0b96a29d27c-9352b3af",
    "group": "TMA SG",
    "area": "",
    "inviteUrl": "https://wedding-us-one.vercel.app/?guest=chi-nhung-e0b96a29d27c-9352b3af"
  },
  {
    "stt": 77,
    "name": "e Bảo",
    "slug": "e-bao-15b74d1cc1c1-c64353c5",
    "group": "TMA SG",
    "area": "",
    "inviteUrl": "https://wedding-us-one.vercel.app/?guest=e-bao-15b74d1cc1c1-c64353c5"
  },
  {
    "stt": 78,
    "name": "em Mai",
    "slug": "em-mai-b0fe155409e0-9179ae7f",
    "group": "TMA SG",
    "area": "",
    "inviteUrl": "https://wedding-us-one.vercel.app/?guest=em-mai-b0fe155409e0-9179ae7f"
  },
  {
    "stt": 79,
    "name": "em Khôi",
    "slug": "em-khoi-943da5d54e5e-67b4cbd4",
    "group": "TMA SG",
    "area": "",
    "inviteUrl": "https://wedding-us-one.vercel.app/?guest=em-khoi-943da5d54e5e-67b4cbd4"
  },
  {
    "stt": 80,
    "name": "em Hò",
    "slug": "em-ho-3ba5f839b189-b4c97072",
    "group": "TMA SG",
    "area": "",
    "inviteUrl": "https://wedding-us-one.vercel.app/?guest=em-ho-3ba5f839b189-b4c97072"
  },
  {
    "stt": 81,
    "name": "a Động",
    "slug": "a-dong-f91b3fd4d0fc-d1421fe5",
    "group": "TMA SG",
    "area": "",
    "inviteUrl": "https://wedding-us-one.vercel.app/?guest=a-dong-f91b3fd4d0fc-d1421fe5"
  },
  {
    "stt": 82,
    "name": "a Luân",
    "slug": "a-luan-b108424571ec-30f7007f",
    "group": "TMA SG",
    "area": "",
    "inviteUrl": "https://wedding-us-one.vercel.app/?guest=a-luan-b108424571ec-30f7007f"
  },
  {
    "stt": 83,
    "name": "a Thành",
    "slug": "a-thanh-678b24164378-f89f37e5",
    "group": "TMA SG",
    "area": "",
    "inviteUrl": "https://wedding-us-one.vercel.app/?guest=a-thanh-678b24164378-f89f37e5"
  },
  {
    "stt": 84,
    "name": "a Đời",
    "slug": "a-doi-170d60a236f5-400d8843",
    "group": "DC13",
    "area": "Quy Nhơn",
    "inviteUrl": "https://wedding-us-one.vercel.app/?guest=a-doi-170d60a236f5-400d8843"
  },
  {
    "stt": 85,
    "name": "a Tuấn",
    "slug": "a-tuan-nguyen-d36fe60b62c3-6794e81f",
    "group": "DC13",
    "area": "",
    "inviteUrl": "https://wedding-us-one.vercel.app/?guest=a-tuan-nguyen-d36fe60b62c3-6794e81f"
  },
  {
    "stt": 86,
    "name": "a Tài",
    "slug": "a-tai-566a533ba2d6-9bcd53bd",
    "group": "DC Khác",
    "area": "",
    "inviteUrl": "https://wedding-us-one.vercel.app/?guest=a-tai-566a533ba2d6-9bcd53bd"
  },
  {
    "stt": 87,
    "name": "Hiếu",
    "slug": "hieu-trinh-471b8227d42f-2d0d5890",
    "group": "DC13",
    "area": "",
    "inviteUrl": "https://wedding-us-one.vercel.app/?guest=hieu-trinh-471b8227d42f-2d0d5890"
  },
  {
    "stt": 88,
    "name": "a Chiến",
    "slug": "a-chien-8133fd9b4855-663f3969",
    "group": "DC Khác",
    "area": "",
    "inviteUrl": "https://wedding-us-one.vercel.app/?guest=a-chien-8133fd9b4855-663f3969"
  },
  {
    "stt": 89,
    "name": "e Linh",
    "slug": "linh-lam-191eea46fd4f-ccf2dd30",
    "group": "DC13",
    "area": "",
    "inviteUrl": "https://wedding-us-one.vercel.app/?guest=linh-lam-191eea46fd4f-ccf2dd30"
  },
  {
    "stt": 90,
    "name": "Lộc",
    "slug": "loc-5de1b12df2c8-82094a70",
    "group": "DC13",
    "area": "",
    "inviteUrl": "https://wedding-us-one.vercel.app/?guest=loc-5de1b12df2c8-82094a70"
  },
  {
    "stt": 91,
    "name": "em Sơn",
    "slug": "em-son-vo-dcd219d68cbf-f8397138",
    "group": "DC13",
    "area": "",
    "inviteUrl": "https://wedding-us-one.vercel.app/?guest=em-son-vo-dcd219d68cbf-f8397138"
  },
  {
    "stt": 92,
    "name": "em Hà",
    "slug": "em-ha-19957a18a74a-268574cf",
    "group": "DC13",
    "area": "",
    "inviteUrl": "https://wedding-us-one.vercel.app/?guest=em-ha-19957a18a74a-268574cf"
  },
  {
    "stt": 93,
    "name": "a Nghĩa",
    "slug": "a-nghia-8f07bb57d020-5ae1c697",
    "group": "DC13",
    "area": "",
    "inviteUrl": "https://wedding-us-one.vercel.app/?guest=a-nghia-8f07bb57d020-5ae1c697"
  },
  {
    "stt": 94,
    "name": "em Mến",
    "slug": "em-men-51bf5886f1c8-96974f85",
    "group": "DC13",
    "area": "",
    "inviteUrl": "https://wedding-us-one.vercel.app/?guest=em-men-51bf5886f1c8-96974f85"
  },
  {
    "stt": 95,
    "name": "em Hậu",
    "slug": "em-hau-9f526b89936c-f36f282e",
    "group": "DC13",
    "area": "",
    "inviteUrl": "https://wedding-us-one.vercel.app/?guest=em-hau-9f526b89936c-f36f282e"
  },
  {
    "stt": 96,
    "name": "a Linh",
    "slug": "a-linh-5abbc3093164-3fafc54f",
    "group": "DC13",
    "area": "",
    "inviteUrl": "https://wedding-us-one.vercel.app/?guest=a-linh-5abbc3093164-3fafc54f"
  },
  {
    "stt": 97,
    "name": "em Luân Hàng",
    "slug": "em-luan-hang-eb517b121baa-dc9332de",
    "group": "DC13",
    "area": "",
    "inviteUrl": "https://wedding-us-one.vercel.app/?guest=em-luan-hang-eb517b121baa-dc9332de"
  },
  {
    "stt": 98,
    "name": "a Quí",
    "slug": "a-qui-79cecb8ce877-b40809eb",
    "group": "DC13",
    "area": "",
    "inviteUrl": "https://wedding-us-one.vercel.app/?guest=a-qui-79cecb8ce877-b40809eb"
  },
  {
    "stt": 99,
    "name": "a Tiến",
    "slug": "a-tien-6577747eb87a-da245fce",
    "group": "DC13",
    "area": "",
    "inviteUrl": "https://wedding-us-one.vercel.app/?guest=a-tien-6577747eb87a-da245fce"
  },
  {
    "stt": 100,
    "name": "Thịnh",
    "slug": "thinh-diep-d5715c1789f8-14c7becd",
    "group": "DC Khác",
    "area": "",
    "inviteUrl": "https://wedding-us-one.vercel.app/?guest=thinh-diep-d5715c1789f8-14c7becd"
  },
  {
    "stt": 101,
    "name": "anh Vũ",
    "slug": "anh-vu-dang-f18b6549d299-f2b99b65",
    "group": "DC13",
    "area": "",
    "inviteUrl": "https://wedding-us-one.vercel.app/?guest=anh-vu-dang-f18b6549d299-f2b99b65"
  },
  {
    "stt": 102,
    "name": "chị Quế",
    "slug": "chi-que-c2f699ffc736-fab47c85",
    "group": "DC13",
    "area": "",
    "inviteUrl": "https://wedding-us-one.vercel.app/?guest=chi-que-c2f699ffc736-fab47c85"
  },
  {
    "stt": 103,
    "name": "a Châu",
    "slug": "a-chau-1d419959ce2c-407964a8",
    "group": "DC13",
    "area": "",
    "inviteUrl": "https://wedding-us-one.vercel.app/?guest=a-chau-1d419959ce2c-407964a8"
  },
  {
    "stt": 104,
    "name": "chị Phương",
    "slug": "chi-phuong-bcad72571481-94362bc5",
    "group": "DC13",
    "area": "",
    "inviteUrl": "https://wedding-us-one.vercel.app/?guest=chi-phuong-bcad72571481-94362bc5"
  },
  {
    "stt": 105,
    "name": "a Phụng",
    "slug": "a-phung-fee0de5cc3bd-829171ab",
    "group": "DC13",
    "area": "",
    "inviteUrl": "https://wedding-us-one.vercel.app/?guest=a-phung-fee0de5cc3bd-829171ab"
  },
  {
    "stt": 106,
    "name": "em Hồng",
    "slug": "em-hong-le-8afb38c3d9e5-73f498a1",
    "group": "DC13",
    "area": "",
    "inviteUrl": "https://wedding-us-one.vercel.app/?guest=em-hong-le-8afb38c3d9e5-73f498a1"
  },
  {
    "stt": 107,
    "name": "chị Qui",
    "slug": "chi-qui-f6aa108dffa6-71283cd7",
    "group": "DC13",
    "area": "",
    "inviteUrl": "https://wedding-us-one.vercel.app/?guest=chi-qui-f6aa108dffa6-71283cd7"
  },
  {
    "stt": 108,
    "name": "Khánh",
    "slug": "khanh-cu-8c9e154e99f7-9c996f53",
    "group": "DC13",
    "area": "",
    "inviteUrl": "https://wedding-us-one.vercel.app/?guest=khanh-cu-8c9e154e99f7-9c996f53"
  },
  {
    "stt": 109,
    "name": "Thời",
    "slug": "thoi-4bf8b44da60e-c6122ad5",
    "group": "DC13",
    "area": "",
    "inviteUrl": "https://wedding-us-one.vercel.app/?guest=thoi-4bf8b44da60e-c6122ad5"
  },
  {
    "stt": 110,
    "name": "em Tú",
    "slug": "em-tu-pham-ea8dfaf89957-89e7933b",
    "group": "DC13",
    "area": "",
    "inviteUrl": "https://wedding-us-one.vercel.app/?guest=em-tu-pham-ea8dfaf89957-89e7933b"
  },
  {
    "stt": 111,
    "name": "a Văn",
    "slug": "a-van-9cddb6a604c5-139c884e",
    "group": "DC13",
    "area": "",
    "inviteUrl": "https://wedding-us-one.vercel.app/?guest=a-van-9cddb6a604c5-139c884e"
  },
  {
    "stt": 112,
    "name": "e Hải",
    "slug": "e-hai-e47110212ab5-8ddb9145",
    "group": "DC13",
    "area": "",
    "inviteUrl": "https://wedding-us-one.vercel.app/?guest=e-hai-e47110212ab5-8ddb9145"
  },
  {
    "stt": 113,
    "name": "e Hiếu",
    "slug": "e-hieu-vo-3e7e26ee3d52-2600d3a1",
    "group": "DC13",
    "area": "",
    "inviteUrl": "https://wedding-us-one.vercel.app/?guest=e-hieu-vo-3e7e26ee3d52-2600d3a1"
  },
  {
    "stt": 114,
    "name": "e Trung",
    "slug": "e-trung-40d571fd6442-f955d2fc",
    "group": "DC13",
    "area": "",
    "inviteUrl": "https://wedding-us-one.vercel.app/?guest=e-trung-40d571fd6442-f955d2fc"
  },
  {
    "stt": 115,
    "name": "Huy",
    "slug": "huy-7eb132117b7b-f11e8787",
    "group": "DC13",
    "area": "",
    "inviteUrl": "https://wedding-us-one.vercel.app/?guest=huy-7eb132117b7b-f11e8787"
  },
  {
    "stt": 116,
    "name": "a Khải",
    "slug": "a-khai-b5ee790c7806-f91f5544",
    "group": "DC13",
    "area": "",
    "inviteUrl": "https://wedding-us-one.vercel.app/?guest=a-khai-b5ee790c7806-f91f5544"
  },
  {
    "stt": 117,
    "name": "Trưởng",
    "slug": "truong-714733a92862-b4e38648",
    "group": "DC13",
    "area": "",
    "inviteUrl": "https://wedding-us-one.vercel.app/?guest=truong-714733a92862-b4e38648"
  },
  {
    "stt": 118,
    "name": "anh Huy",
    "slug": "anh-huy-tran-4d8db4e4abd3-61324a95",
    "group": "DC13",
    "area": "",
    "inviteUrl": "https://wedding-us-one.vercel.app/?guest=anh-huy-tran-4d8db4e4abd3-61324a95"
  },
  {
    "stt": 119,
    "name": "Huy",
    "slug": "huy-nguyen-13916d966288-c4bd5d8d",
    "group": "DC13",
    "area": "",
    "inviteUrl": "https://wedding-us-one.vercel.app/?guest=huy-nguyen-13916d966288-c4bd5d8d"
  },
  {
    "stt": 120,
    "name": "em Nga",
    "slug": "em-nga-nguyen-00140a9ac9f0-16a743ca",
    "group": "DC13",
    "area": "",
    "inviteUrl": "https://wedding-us-one.vercel.app/?guest=em-nga-nguyen-00140a9ac9f0-16a743ca"
  },
  {
    "stt": 121,
    "name": "a Đạt",
    "slug": "a-dat-a9c369498232-5b3fa616",
    "group": "DC13",
    "area": "",
    "inviteUrl": "https://wedding-us-one.vercel.app/?guest=a-dat-a9c369498232-5b3fa616"
  },
  {
    "stt": 122,
    "name": "a Tuấn",
    "slug": "a-tuan-dang-2a690074e54d-d04d9034",
    "group": "DC Khác",
    "area": "",
    "inviteUrl": "https://wedding-us-one.vercel.app/?guest=a-tuan-dang-2a690074e54d-d04d9034"
  },
  {
    "stt": 123,
    "name": "a Hùng",
    "slug": "a-hung-345cb895badf-d56be83e",
    "group": "DC Khác",
    "area": "",
    "inviteUrl": "https://wedding-us-one.vercel.app/?guest=a-hung-345cb895badf-d56be83e"
  },
  {
    "stt": 124,
    "name": "a Dũng",
    "slug": "a-dung-le-543f112bd553-85d69189",
    "group": "DC Khác",
    "area": "",
    "inviteUrl": "https://wedding-us-one.vercel.app/?guest=a-dung-le-543f112bd553-85d69189"
  },
  {
    "stt": 125,
    "name": "a Tường",
    "slug": "a-tuong-d9411b109e8a-f79c1ed1",
    "group": "DC Khác",
    "area": "",
    "inviteUrl": "https://wedding-us-one.vercel.app/?guest=a-tuong-d9411b109e8a-f79c1ed1"
  },
  {
    "stt": 126,
    "name": "a Thiết",
    "slug": "a-thiet-82cb95ace543-b1489c74",
    "group": "DC Khác",
    "area": "",
    "inviteUrl": "https://wedding-us-one.vercel.app/?guest=a-thiet-82cb95ace543-b1489c74"
  },
  {
    "stt": 127,
    "name": "a Phước",
    "slug": "a-phuoc-f897618987cd-2537a807",
    "group": "DC Khác",
    "area": "",
    "inviteUrl": "https://wedding-us-one.vercel.app/?guest=a-phuoc-f897618987cd-2537a807"
  },
  {
    "stt": 128,
    "name": "a Sướng",
    "slug": "a-suong-49e098696c5c-0087f7e7",
    "group": "DC Khác",
    "area": "",
    "inviteUrl": "https://wedding-us-one.vercel.app/?guest=a-suong-49e098696c5c-0087f7e7"
  },
  {
    "stt": 129,
    "name": "chị Trâm",
    "slug": "chi-tram-ff5d8f40aebc-8eafd2e6",
    "group": "DC Khác",
    "area": "",
    "inviteUrl": "https://wedding-us-one.vercel.app/?guest=chi-tram-ff5d8f40aebc-8eafd2e6"
  },
  {
    "stt": 130,
    "name": "Yên",
    "slug": "truong-yen-86d314b9cb7a-4a61f083",
    "group": "Ae xã giao",
    "area": "Phú Yên",
    "inviteUrl": "https://wedding-us-one.vercel.app/?guest=truong-yen-86d314b9cb7a-4a61f083"
  },
  {
    "stt": 131,
    "name": "a Dẽ",
    "slug": "a-de-0723e6ab3b24-4c09573d",
    "group": "Ae xã giao",
    "area": "Quy Nhơn",
    "inviteUrl": "https://wedding-us-one.vercel.app/?guest=a-de-0723e6ab3b24-4c09573d"
  },
  {
    "stt": 132,
    "name": "e Sơn",
    "slug": "e-son-dinh-4b3d3189a88b-0faaecba",
    "group": "DC Khác",
    "area": "",
    "inviteUrl": "https://wedding-us-one.vercel.app/?guest=e-son-dinh-4b3d3189a88b-0faaecba"
  },
  {
    "stt": 133,
    "name": "cô Sáu",
    "slug": "ma-nuoi-me-duy-9fc448fbc471-1dc6331b",
    "group": "Bạn của gia đình",
    "area": "Quy Nhơn",
    "inviteUrl": "https://wedding-us-one.vercel.app/?guest=ma-nuoi-me-duy-9fc448fbc471-1dc6331b"
  },
  {
    "stt": 134,
    "name": "anh Hai",
    "slug": "nha-anh-2-duy-5981e5f7ba8b-888b8f27",
    "group": "Bạn của gia đình",
    "area": "Quy Nhơn",
    "inviteUrl": "https://wedding-us-one.vercel.app/?guest=nha-anh-2-duy-5981e5f7ba8b-888b8f27"
  }
]